startfast/__init__.py
startfast/cli.py
startfast/core/__init__.py
startfast/core/config.py
startfast/generators/__init__.py
startfast/generators/base_generator.py
startfast/generators/project_generator.py
startfast/generators/file_generators/__init__.py
startfast/generators/file_generators/api_generator.py
startfast/generators/file_generators/auth_generator.py
startfast/generators/file_generators/celery_generator.py
startfast/generators/file_generators/config_generator.py
startfast/generators/file_generators/database_generator.py
startfast/generators/file_generators/docker_generator.py
startfast/generators/file_generators/docs_generator.py
startfast/generators/file_generators/environment_generator.py
startfast/generators/file_generators/main_app_generator.py
startfast/generators/file_generators/monitoring_generator.py
startfast/generators/file_generators/requirements_generator.py
startfast/generators/file_generators/schemas_generator.py
startfast/generators/file_generators/tests_generator.py
startfast/generators/file_generators/utils_generator.py
startfast-1.0.0.dist-info/licenses/LICENSE
startfast-1.0.0.dist-info/METADATA
startfast-1.0.0.dist-info/WHEEL
startfast-1.0.0.dist-info/entry_points.txt
startfast-1.0.0.dist-info/top_level.txt
startfast-1.0.0.dist-info/RECORD
